wix-elk-logger/__init__.py
wix-elk-logger/elk-logger.py
wix-elk-logger/elk_logger.py
wix_elk_logger/__init__.py
wix_elk_logger/elk-logger.py
wix_elk_logger/elk_logger.py
wix_elk_logger-1.0.6.dist-info/METADATA
wix_elk_logger-1.0.6.dist-info/WHEEL
wix_elk_logger-1.0.6.dist-info/top_level.txt
wix_elk_logger-1.0.6.dist-info/RECORD
